hogyoku/__init__.py
hogyoku/code.py
hogyoku/spark.py
hogyoku-0.1.15.dist-info/METADATA
hogyoku-0.1.15.dist-info/WHEEL
hogyoku-0.1.15.dist-info/top_level.txt
hogyoku-0.1.15.dist-info/RECORD
