Metadata-Version: 2.1
Name: hogyoku
Version: 0.1.15
Summary: hogyoku
Home-page: https://github.com/JianweiChen/hogyoku
Author: chenjianwei
Author-email: 1572069841@qq.com
License: MIT
Platform: UNKNOWN
